odoo/addons/l10n_ro_account_edi_ubl/README.rst
odoo/addons/l10n_ro_account_edi_ubl/__init__.py
odoo/addons/l10n_ro_account_edi_ubl/__manifest__.py
odoo/addons/l10n_ro_account_edi_ubl/data/account_edi_data.xml
odoo/addons/l10n_ro_account_edi_ubl/data/ubl_templates.xml
odoo/addons/l10n_ro_account_edi_ubl/i18n/l10n_ro_account_edi_ubl.pot
odoo/addons/l10n_ro_account_edi_ubl/i18n/ro.po
odoo/addons/l10n_ro_account_edi_ubl/migrations/14.0.1.26.3/post_migration.py
odoo/addons/l10n_ro_account_edi_ubl/migrations/14.0.1.35.4/pre-migration.py
odoo/addons/l10n_ro_account_edi_ubl/models/__init__.py
odoo/addons/l10n_ro_account_edi_ubl/models/account_edi_format.py
odoo/addons/l10n_ro_account_edi_ubl/models/account_edi_xml_cius_ro.py
odoo/addons/l10n_ro_account_edi_ubl/models/account_move.py
odoo/addons/l10n_ro_account_edi_ubl/models/ir_actions_report.py
odoo/addons/l10n_ro_account_edi_ubl/models/l10n_ro_account_anaf_sync_scope.py
odoo/addons/l10n_ro_account_edi_ubl/models/product.py
odoo/addons/l10n_ro_account_edi_ubl/models/res_company.py
odoo/addons/l10n_ro_account_edi_ubl/models/res_config_settings.py
odoo/addons/l10n_ro_account_edi_ubl/models/res_partner.py
odoo/addons/l10n_ro_account_edi_ubl/readme/CONFIGURE.rst
odoo/addons/l10n_ro_account_edi_ubl/readme/CONTRIBUTORS.rst
odoo/addons/l10n_ro_account_edi_ubl/readme/DESCRIPTION.rst
odoo/addons/l10n_ro_account_edi_ubl/security/ir.model.access.csv
odoo/addons/l10n_ro_account_edi_ubl/static/description/anaf.png
odoo/addons/l10n_ro_account_edi_ubl/static/description/anaf.svg
odoo/addons/l10n_ro_account_edi_ubl/static/description/icon.png
odoo/addons/l10n_ro_account_edi_ubl/static/description/icon.svg
odoo/addons/l10n_ro_account_edi_ubl/static/description/index.html
odoo/addons/l10n_ro_account_edi_ubl/tests/3828.zip
odoo/addons/l10n_ro_account_edi_ubl/tests/5004552043.zip
odoo/addons/l10n_ro_account_edi_ubl/tests/5004879752.zip
odoo/addons/l10n_ro_account_edi_ubl/tests/__init__.py
odoo14_addon_l10n_ro_account_edi_ubl-14.0.1.36.0.dist-info/METADATA
odoo14_addon_l10n_ro_account_edi_ubl-14.0.1.36.0.dist-info/WHEEL
odoo14_addon_l10n_ro_account_edi_ubl-14.0.1.36.0.dist-info/top_level.txt
odoo14_addon_l10n_ro_account_edi_ubl-14.0.1.36.0.dist-info/RECORD
