Metadata-Version: 2.1
Name: odoo14-addon-l10n_ro_account_edi_ubl
Version: 14.0.1.36.0
Summary: Romania - eFactura - Account EDI UBL
Home-page: https://github.com/OCA/l10n-romania
Author: Terrabit,NextERP Romania,Odoo Community Association (OCA)
Author-email: support@odoo-community.org
License: AGPL-3
Classifier: Programming Language :: Python
Classifier: Framework :: Odoo
Classifier: Framework :: Odoo :: 14.0
Classifier: License :: OSI Approved :: GNU Affero General Public License v3
Classifier: Development Status :: 6 - Mature
Requires-Python: >=3.6
Requires-Dist: odoo14-addon-l10n-ro-account-anaf-sync
Requires-Dist: odoo<14.1dev,>=14.0a
